pymg/__init__.py
pymg/pymg.py
pymg-2.0.1.dist-info/LICENSE
pymg-2.0.1.dist-info/METADATA
pymg-2.0.1.dist-info/WHEEL
pymg-2.0.1.dist-info/dependency_links.txt
pymg-2.0.1.dist-info/entry_points.txt
pymg-2.0.1.dist-info/top_level.txt
pymg-2.0.1.dist-info/RECORD
