Metadata-Version: 2.1
Name: pymg
Version: 2.0.1
Summary: pymg is a CLI tool that can interpret Python files by the Python interpreter and display the error message in a more readable way if an exception occurs.
Home-page: https://github.com/mimseyedi/pymg
Author: mimseyedi
Author-email: mim.seyedi@gmail.com
License: GNU General Public License v3 (GPLv3)
Classifier: License :: OSI Approved :: GNU General Public License v3 (GPLv3)
Classifier: Programming Language :: Python :: 3
Classifier: Programming Language :: Python :: 3.10
Classifier: Programming Language :: Python :: 3.11
Requires-Python: >=3.11
License-File: LICENSE
Requires-Dist: rich
Requires-Dist: click
Requires-Dist: requests
